tum_exam_scripts/__init__.py
tum_exam_scripts/enums.py
tum_exam_scripts/logic/__init__.py
tum_exam_scripts/logic/pdf_printing.py
tum_exam_scripts/main.py
tum_exam_scripts/pdf_commands.py
tum_exam_scripts/shared.py
tum_exam_scripts/utils/__init__.py
tum_exam_scripts/utils/command.py
tum_exam_scripts/utils/password_handling.py
tum_exam_scripts/utils/website.py
tum_exam_scripts-0.1.7.dist-info/entry_points.txt
tum_exam_scripts-0.1.7.dist-info/LICENSE
tum_exam_scripts-0.1.7.dist-info/WHEEL
tum_exam_scripts-0.1.7.dist-info/METADATA
tum_exam_scripts-0.1.7.dist-info/RECORD
