Metadata-Version: 2.1
Name: tum-exam-scripts
Version: 0.1.7
Summary: 
Home-page: https://github.com/pstoeckle/TUMExam-Scripts
License: Apache-2.0
Author: Patrick Stöckle
Author-email: patrick.stoeckle@tum.de
Maintainer: Patrick Stöckle
Maintainer-email: patrick.stoeckle@tum.de
Requires-Python: >=3.7,<4.0
Classifier: License :: OSI Approved :: Apache Software License
Classifier: Programming Language :: Python :: 3
Classifier: Programming Language :: Python :: 3.7
Classifier: Programming Language :: Python :: 3.8
Classifier: Programming Language :: Python :: 3.9
Classifier: Programming Language :: Python :: 3.10
Requires-Dist: helium (>=3.0.8,<4.0.0)
Requires-Dist: keyring (>=23.11.0,<24.0.0)
Requires-Dist: tqdm (>=4.64.1,<5.0.0)
Requires-Dist: typer (>=0.7.0,<0.8.0)
Project-URL: Repository, https://github.com/pstoeckle/TUMExam-Scripts
